{
    "CSS131104:224955+132821": {
        "name": "CSS131104:224955+132821",
        "aliases": [
            "CSS131104:224955+132821"
        ],
        "sources": [
            {
                "name": "<a href='http://www.rochesterastronomy.org/snimages/snredshiftall.html'>Latest Supernovae</a>",
                "alias": "1",
                "secondary": true
            },
            {
                "name": "<a href='http://www.astronomerstelegram.org/?read=5659'>ATEL 5659</a>",
                "alias": "2"
            }
        ],
        "photometry": [
            {
                "timeunit": "MJD",
                "time": "56599.5",
                "band": "",
                "abmag": "18.8",
                "source": "2,1"
            }
        ],
        "snra": "22:49:55.03",
        "sndec": "+13:28:21.2",
        "discoverday": "3",
        "discovermonth": "11",
        "discoveryear": "2013",
        "discoverer": "CRTS",
        "maxyear": "2013",
        "maxmonth": "11",
        "maxday": "3",
        "maxappmag": "18.8"
    }
}