{
    "CSS100209:035248+212505": {
        "name": "CSS100209:035248+212505",
        "aliases": [
            "CSS100209:035248+212505"
        ],
        "sources": [
            {
                "name": "<a href='http://www.rochesterastronomy.org/snimages/snredshiftall.html'>Latest Supernovae</a>",
                "alias": "1",
                "secondary": true
            },
            {
                "name": "<a href='http://www.astronomerstelegram.org/?read=2447'>ATEL 2447</a>",
                "alias": "2"
            }
        ],
        "photometry": [
            {
                "timeunit": "MJD",
                "time": "55235.5",
                "band": "",
                "abmag": "18.7",
                "source": "2,1"
            }
        ],
        "snra": "03:52:48.06",
        "sndec": "+21:25:05.4",
        "discoverday": 8,
        "discovermonth": 2,
        "discoveryear": 2010,
        "discoverer": "CRTS",
        "maxyear": 2010,
        "maxmonth": 2,
        "maxday": 8
    }
}