{
    "iPTF15dik": {
        "name": "iPTF15dik",
        "aliases": [
            "iPTF15dik"
        ],
        "sources": [
            {
                "name": "<a href='http://www.rochesterastronomy.org/snimages/snredshiftall.html'>Latest Supernovae</a>",
                "alias": "1",
                "secondary": true
            },
            {
                "name": "<a href='http://www.astronomerstelegram.org/?read=8240'>ATEL 8240</a>",
                "alias": "2"
            }
        ],
        "photometry": [
            {
                "timeunit": "MJD",
                "time": "57305.5",
                "band": "",
                "abmag": "20.7",
                "source": "2,1"
            }
        ],
        "claimedtype": "Ia",
        "snra": "00:00:30.84",
        "sndec": "+04:30:19.01",
        "discoverday": "10",
        "discovermonth": "10",
        "discoveryear": "2015",
        "redshift": "0.14",
        "discoverer": "PTF",
        "maxyear": "2015",
        "maxmonth": "10",
        "maxday": "10",
        "maxappmag": "20.7",
        "hvel": "39100",
        "lumdist": "683",
        "maxabsmag": "-18.5"
    }
}