{
    "K0911-001": {
        "name": "K0911-001",
        "aliases": [
            "K0911-001"
        ],
        "sources": [
            {
                "name": "<a href='http://www.rochesterastronomy.org/snimages/snredshiftall.html'>Latest Supernovae</a>",
                "alias": "1",
                "secondary": true
            },
            {
                "name": "<a href='http://www.cbat.eps.harvard.edu/CBAT_PSN.html'>CBAT_PSN</a>",
                "alias": "2"
            }
        ],
        "photometry": [
            {
                "timeunit": "MJD",
                "time": "55155.5",
                "band": "",
                "abmag": "19.5",
                "source": "2,1"
            }
        ],
        "snra": "12:10:05.02",
        "sndec": "+43:26:42.6",
        "discoverday": "20",
        "discovermonth": "11",
        "discoveryear": "2009",
        "discoverer": "Ella Sanders",
        "maxyear": "2009",
        "maxmonth": "11",
        "maxday": "20",
        "maxappmag": "19.5"
    }
}