{
    "LSQ15z": {
        "name": "LSQ15z",
        "aliases": [
            "LSQ15z"
        ],
        "sources": [
            {
                "name": "<a href='http://www.rochesterastronomy.org/snimages/snredshiftall.html'>Latest Supernovae</a>",
                "alias": "1",
                "secondary": true
            },
            {
                "name": "<a href='http://www.astronomerstelegram.org/?read=6928'>ATEL 6928</a>",
                "alias": "2"
            },
            {
                "name": "Kunihiro Shima",
                "alias": "3"
            }
        ],
        "photometry": [
            {
                "timeunit": "MJD",
                "time": "57038.5",
                "band": "",
                "abmag": "17.0",
                "source": "2,1"
            },
            {
                "timeunit": "MJD",
                "time": "57039.8007",
                "band": "U",
                "abmag": "17.0",
                "source": "3,1"
            }
        ],
        "claimedtype": "Ia",
        "snra": "13:08:22.48",
        "sndec": "-08:43:57.8",
        "discoverday": 16,
        "discovermonth": 1,
        "discoveryear": 2015,
        "redshift": 0.07,
        "discoverer": "La Silla-QUEST",
        "maxyear": 2015,
        "maxmonth": 1,
        "maxday": 16
    }
}