{
    "OGLE-2014-SN-168": {
        "name": "OGLE-2014-SN-168",
        "aliases": [
            "OGLE-2014-SN-168"
        ],
        "sources": [
            {
                "name": "<a href='http://www.rochesterastronomy.org/snimages/snredshiftall.html'>Latest Supernovae</a>",
                "alias": "1",
                "secondary": true
            },
            {
                "name": "<a href='http://www.astronomerstelegram.org/?read=6784'>ATEL 6784</a>",
                "alias": "2"
            }
        ],
        "photometry": [
            {
                "timeunit": "MJD",
                "time": "56986.5",
                "band": "",
                "abmag": "20.0",
                "source": "2,1"
            }
        ],
        "snra": "01:25:50.40",
        "sndec": "-75:43:27.4",
        "discoverday": 25,
        "discovermonth": 11,
        "discoveryear": 2014,
        "discoverer": "OGLE-IV wide field survey",
        "maxyear": 2014,
        "maxmonth": 11,
        "maxday": 25
    }
}