{
    "SN2010ic": {
        "name": "SN2010ic",
        "aliases": [
            "SN2010ic"
        ],
        "sources": [
            {
                "name": "<a href='http://www.rochesterastronomy.org/snimages/snredshiftall.html'>Latest Supernovae</a>",
                "alias": "1",
                "secondary": true
            },
            {
                "name": "<a href='http://www.cbat.eps.harvard.edu/iau/cbet/002400/CBET002465.txt'>CBET 2465</a>",
                "alias": "2"
            },
            {
                "name": "<a href='http://adsabs.harvard.edu/abs/2012A%26A...538A.120L'>2012A&A...538A.120L</a>",
                "alias": "3"
            }
        ],
        "photometry": [
            {
                "timeunit": "MJD",
                "time": "55458.5",
                "band": "",
                "abmag": "16.4",
                "source": "2,1"
            }
        ],
        "discoveryear": "2010",
        "discoverday": "19",
        "discovermonth": "9",
        "host": "UGC 11983",
        "claimedtype": "II",
        "hvel": "4900",
        "galra": "221903",
        "galdec": "+331946",
        "snra": "22:19:04.35",
        "sndec": "+33:19:46.9",
        "discoverer": "LOSS",
        "redshift": "0.0165",
        "maxyear": "2010",
        "maxmonth": "9",
        "maxday": "19",
        "maxappmag": "16.4",
        "lumdist": "73.9",
        "maxabsmag": "-17.9"
    }
}