{
    "SN2008cs": {
        "name": "SN2008cs",
        "aliases": [
            "SN2008cs"
        ],
        "sources": [
            {
                "name": "<a href='http://adsabs.harvard.edu/abs/2012A%26A...538A.120L'>2012A&A...538A.120L</a>",
                "alias": "1"
            }
        ],
        "photometry": [
            {
                "timeunit": "MJD",
                "time": "54577.0",
                "band": "K",
                "abmag": "17",
                "source": "1"
            }
        ],
        "discoveryear": "2008",
        "discovermonth": "4",
        "discoverday": "21"
    }
}