{
    "SN2013cd": {
        "name": "SN2013cd",
        "aliases": [
            "SN2013cd",
            "PSN J08164900+6029285"
        ],
        "sources": [
            {
                "name": "<a href='http://www.rochesterastronomy.org/snimages/snredshiftall.html'>Latest Supernovae</a>",
                "alias": "1",
                "secondary": true
            },
            {
                "name": "<a href='http://www.cbat.eps.harvard.edu/iau/cbet/003500/CBET003514.txt'>CBET 3514</a>",
                "alias": "2"
            }
        ],
        "photometry": [
            {
                "timeunit": "MJD",
                "time": "56424.5",
                "band": "",
                "abmag": "16.7",
                "source": "2,1"
            }
        ],
        "discoveryear": "2013",
        "discoverday": "12",
        "discovermonth": "5",
        "host": "UGC 4294",
        "claimedtype": "Ia",
        "hvel": "11700",
        "galra": "081649",
        "galdec": "+602935",
        "snra": "08:16:49.00",
        "sndec": "+60:29:28.5",
        "discoverer": "Doug Rich",
        "redshift": "0.039080",
        "maxyear": "2013",
        "maxmonth": "5",
        "maxday": "12",
        "maxappmag": "16.7",
        "z": "0.0398",
        "lumdist": "180.0",
        "maxabsmag": "-20.0"
    }
}