{
    "SNF20080626-002": {
        "name": "SNF20080626-002",
        "aliases": [
            "SNF20080626-002"
        ],
        "sources": [
            {
                "name": "<a href='http://www.rochesterastronomy.org/snimages/snredshiftall.html'>Latest Supernovae</a>",
                "alias": "1",
                "secondary": true
            },
            {
                "name": "<a href='http://snfactory.lbl.gov/'>SN Factory</a>",
                "alias": "2"
            }
        ],
        "photometry": [
            {
                "timeunit": "MJD",
                "time": "54642.5",
                "band": "",
                "abmag": "16.7",
                "source": "2,1"
            }
        ],
        "claimedtype": "Ia",
        "snra": "22:45:02.49",
        "sndec": "+08:56:39.0",
        "discoverday": "25",
        "discovermonth": "6",
        "discoveryear": "2008",
        "discoverer": "Nearby Supernova Factory",
        "maxyear": "2008",
        "maxmonth": "6",
        "maxday": "25",
        "maxappmag": "16.7"
    }
}